netora/__init__.py
netora/__main__.py
netora/connection.py
netora/getinfo.py
netora/netora.py
netora/validation.py
netora/resources/currencies.py
netora-0.24.0.dist-info/METADATA
netora-0.24.0.dist-info/WHEEL
netora-0.24.0.dist-info/entry_points.txt
netora-0.24.0.dist-info/top_level.txt
netora-0.24.0.dist-info/RECORD
