Metadata-Version: 2.4
Name: netora
Version: 0.24.0
Summary: Quickly uncover details and geolocation for any IP address
Author-email: nativevoid <0x4E56@proton.me>
Maintainer-email: nativevoid <0x4E56@proton.me>
Project-URL: Homepage, https://nativevoid.mintlify.app
Project-URL: Repository, https://github.com/nativevoid/netora
Project-URL: Bug Tracker, https://github.com/nativevoid/netora/issues
Keywords: geolocation,IP,OSINT
Classifier: Development Status :: 5 - Production/Stable
Classifier: Intended Audience :: Developers
Classifier: Intended Audience :: Information Technology
Classifier: Natural Language :: English
Classifier: Operating System :: OS Independent
Classifier: Programming Language :: Python :: 3
Classifier: Topic :: Security
Requires-Python: >=3.6
Requires-Dist: requests>=2.25
Requires-Dist: colorama>=0.4.6
Requires-Dist: tzdata>=2025.2
Requires-Dist: backports.zoneinfo>=0.2.1; python_version < "3.9"
